error_links/__init__.py
error_links/__main__.py
error_links-0.3.0.dist-info/METADATA
error_links-0.3.0.dist-info/WHEEL
error_links-0.3.0.dist-info/entry_points.txt
error_links-0.3.0.dist-info/RECORD
