Metadata-Version: 2.1
Name: error-links
Version: 0.3.0
Summary: Adds helpful links to the REPL when an exception happens.
Author: Rodrigo Girão Serrão
Author-email: rodrigo@mathspp.com
Requires-Python: >=3.8,<4.0
Classifier: Programming Language :: Python :: 3
Classifier: Programming Language :: Python :: 3.8
Classifier: Programming Language :: Python :: 3.9
Classifier: Programming Language :: Python :: 3.10
Classifier: Programming Language :: Python :: 3.11
Requires-Dist: rich (>=13.6.0,<14.0.0)
